yms_faster_rcnn/__init__.py
yms_faster_rcnn/version.py
yms_faster_rcnn/backbone/__init__.py
yms_faster_rcnn/backbone/feature_pyramid_network.py
yms_faster_rcnn/backbone/mobilenetv2_model.py
yms_faster_rcnn/backbone/resnet50_fpn_model.py
yms_faster_rcnn/backbone/vgg_model.py
yms_faster_rcnn/data_process/__init__.py
yms_faster_rcnn/data_process/concat_images.py
yms_faster_rcnn/data_process/count_image_types.py
yms_faster_rcnn/data_process/data_process.py
yms_faster_rcnn/data_process/extract_categories.py
yms_faster_rcnn/data_process/extract_diffs.py
yms_faster_rcnn/data_process/extract_filenames.py
yms_faster_rcnn/data_process/filter_by_category.py
yms_faster_rcnn/data_process/rename.py
yms_faster_rcnn/data_process/separate_annotated_categories.py
yms_faster_rcnn/data_process/split_train_val.py
yms_faster_rcnn/data_process/util.py
yms_faster_rcnn/network_files/__init__.py
yms_faster_rcnn/network_files/boxes.py
yms_faster_rcnn/network_files/det_utils.py
yms_faster_rcnn/network_files/faster_rcnn_framework.py
yms_faster_rcnn/network_files/image_list.py
yms_faster_rcnn/network_files/roi_head.py
yms_faster_rcnn/network_files/rpn_function.py
yms_faster_rcnn/network_files/transform.py
yms_faster_rcnn/result_calculation/__init__.py
yms_faster_rcnn/result_calculation/draw.py
yms_faster_rcnn/result_calculation/xml_detection_stats.py
yms_faster_rcnn/train/__init__.py
yms_faster_rcnn/train/change_backbone_with_fpn.py
yms_faster_rcnn/train/change_backbone_without_fpn.py
yms_faster_rcnn/train/draw_box_utils.py
yms_faster_rcnn/train/muti_predict.py
yms_faster_rcnn/train/predict.py
yms_faster_rcnn/train/split_data.py
yms_faster_rcnn/train/test.py
yms_faster_rcnn/train/train.py
yms_faster_rcnn/train/train_mobilenetv2.py
yms_faster_rcnn/train/train_multi_GPU.py
yms_faster_rcnn/train/train_muti_gpu.py
yms_faster_rcnn/train/train_res50_fpn.py
yms_faster_rcnn/train/ttf_test.py
yms_faster_rcnn/train/val.py
yms_faster_rcnn/train/validation.py
yms_faster_rcnn/train_utils/__init__.py
yms_faster_rcnn-0.1.18.dist-info/licenses/LICENSE
yms_faster_rcnn-0.1.18.dist-info/METADATA
yms_faster_rcnn-0.1.18.dist-info/WHEEL
yms_faster_rcnn-0.1.18.dist-info/top_level.txt
yms_faster_rcnn-0.1.18.dist-info/RECORD
