Metadata-Version: 2.4
Name: yms_faster_rcnn
Version: 0.1.18
Summary: My awesome package
Author-email: yms <11@qq.com>
License-Expression: MIT
License-File: LICENSE
Dynamic: license-file
